[{
    "pic": "http://img3x8.ddimg.cn/1/20/24027598-1_l_1.jpg",
    "title": "中国历史研究法（跟大师学国学・精装版）",
    "url": "http://product.dangdang.com/24027598.html",
    "author": "梁启超　著",
    "time": "2016-06-01",
    "press": "中华书局",
    "prices": "¥21.30"
}, {
    "pic": "http://img3x4.ddimg.cn/96/16/24027594-1_l_1.jpg",
    "title": "中国近代史新编（跟大师学国学・精装版）",
    "url": "http://product.dangdang.com/24027594.html",
    "author": "蒋廷黻　著",
    "time": "2016-06-01",
    "press": "中华书局",
    "prices": "¥24.60"
}, {
    "pic": "http://img3x3.ddimg.cn/95/15/24027593-1_l_1.jpg",
    "title": "史学方法导论（跟大师学国学・精装版）",
    "url": "http://product.dangdang.com/24027593.html",
    "author": "傅斯年　著",
    "time": "2016-06-01",
    "press": "中华书局",
    "prices": "¥18.00"
}, {
    "pic": "http://img3x0.ddimg.cn/92/12/24027590-1_l_1.jpg",
    "title": "明史讲义（跟大师学国学・精装版）",
    "url": "http://product.dangdang.com/24027590.html",
    "author": "孟森　著",
    "time": "2016-06-01",
    "press": "中华书局",
    "prices": "¥23.00"
}, {
    "pic": "http://img3x2.ddimg.cn/74/31/24027572-1_l_1.jpg",
    "title": "中国史纲（跟大师学国学・精装版）",
    "url": "http://product.dangdang.com/24027572.html",
    "author": "张荫麟　著",
    "time": "2016-06-01",
    "press": "中华书局",
    "prices": "¥23.00"
}, {
    "pic": "http://img3x1.ddimg.cn/73/30/24027571-1_l_1.jpg",
    "title": "中国历史研究法补编（跟大师学国学・精装版）",
    "url": "http://product.dangdang.com/24027571.html",
    "author": "梁启超　著",
    "time": "2016-06-01",
    "press": "中华书局",
    "prices": "¥20.50"
}, {
    "pic": "http://img3x4.ddimg.cn/24/4/24023364-1_l_2.jpg",
    "title": "说天国：从杨秀清到李秀成",
    "url": "http://product.dangdang.com/24023364.html",
    "author": "陶短房　著",
    "time": "2016-06-01",
    "press": "中华书局",
    "prices": "¥36.90"
}, {
    "pic": "http://img3x3.ddimg.cn/23/3/24023363-1_l_2.jpg",
    "title": "说天国：从石达开到陈玉成",
    "url": "http://product.dangdang.com/24023363.html",
    "author": "陶短房　著",
    "time": "2016-06-01",
    "press": "中华书局",
    "prices": "¥34.40"
}, {
    "pic": "http://img3x6.ddimg.cn/15/15/24018306-1_l_5.jpg",
    "title": "三国谜案",
    "url": "http://product.dangdang.com/24018306.html",
    "author": "辣笔小球",
    "time": "2016-08-01",
    "press": "二十一世纪出版社",
    "prices": "¥21.90"
}, {
    "pic": "http://img3x3.ddimg.cn/73/5/24016483-1_l_5.jpg",
    "title": "明朝历史的教训",
    "url": "http://product.dangdang.com/24016483.html",
    "author": "吴晗",
    "time": "2016-08-01",
    "press": "台海出版社",
    "prices": "¥23.40"
}, {
    "pic": "http://img3x9.ddimg.cn/30/5/24014559-1_l_1.jpg",
    "title": "海明威家的厄运：一部家族回忆录",
    "url": "http://product.dangdang.com/24014559.html",
    "time": "2016-08-01",
    "press": "上海三联书店",
    "prices": "¥32.30"
}, {
    "pic": "http://img3x3.ddimg.cn/44/36/24008633-1_l_2.jpg",
    "title": "中国历史纪年表",
    "url": "http://product.dangdang.com/24008633.html",
    "author": "万国鼎 编、万斯年，陈梦家 补订",
    "time": "1978-11-01",
    "press": "中华书局",
    "prices": "¥16.20"
}, {
    "pic": "http://img3x8.ddimg.cn/29/21/24008618-1_l_6.jpg",
    "title": "新出魏晋南北朝墓志疏证（修订本）（北京大学中国古代史研究中心丛刊）",
    "url": "http://product.dangdang.com/24008618.html",
    "author": "罗新、叶炜 著",
    "time": "2016-05-01",
    "press": "中华书局",
    "prices": "¥149.60"
}, {
    "pic": "http://img3x7.ddimg.cn/90/1/24039567-1_l_3.jpg",
    "title": "苍狼逐鹿――蒙宋百年战争史",
    "url": "http://product.dangdang.com/24039567.html",
    "author": "赵恺 郭强",
    "time": "2016-09-01",
    "press": "团结出版社",
    "prices": "¥27.60"
}, {
    "pic": "http://img3x4.ddimg.cn/0/4/24037794-1_l_1.jpg",
    "title": "最后的大队：蒋介石与日本军人",
    "url": "http://product.dangdang.com/24037794.html",
    "author": "野岛刚（Nojima Tsuyoshi）；芦荻",
    "time": "2016-10-01",
    "press": "社会科学文献出版社",
    "prices": "¥43.50"
}, {
    "pic": "http://img3x0.ddimg.cn/93/1/24027690-1_l_5.jpg",
    "title": "后现代史学理论读本",
    "url": "http://product.dangdang.com/24027690.html",
    "author": "彭刚",
    "time": "2016-09-05",
    "press": "北京大学出版社",
    "prices": "¥39.20"
}, {
    "pic": "http://img3x4.ddimg.cn/86/6/24027584-1_l_1.jpg",
    "title": "中国八大诗人（跟大师学国学・精装版）",
    "url": "http://product.dangdang.com/24027584.html",
    "author": "胡怀琛　著",
    "time": "2016-06-01",
    "press": "中华书局",
    "prices": "¥20.50"
}, {
    "pic": "http://img3x9.ddimg.cn/81/1/24027579-1_l_1.jpg",
    "title": "中国的文化与思想（跟大师学国学・精装版）",
    "url": "http://product.dangdang.com/24027579.html",
    "author": "常乃 著",
    "time": "2016-06-01",
    "press": "中华书局",
    "prices": "¥23.00"
}, {
    "pic": "http://img3x8.ddimg.cn/80/0/24027578-1_l_1.jpg",
    "title": "史讳举例（跟大师学国学・精装版）",
    "url": "http://product.dangdang.com/24027578.html",
    "author": "陈垣　著",
    "time": "2016-06-01",
    "press": "中华书局",
    "prices": "¥23.00"
}, {
    "pic": "http://img3x3.ddimg.cn/43/30/24014473-1_l_2.jpg",
    "title": "豆腐与威士忌：日本的过去、未来及其他",
    "url": "http://product.dangdang.com/24014473.html",
    "author": "（日）野岛刚　著",
    "time": "2016-08-01",
    "press": "上海译文出版社",
    "prices": "¥28.00"
}, {
    "pic": "http://img3x5.ddimg.cn/24/35/24025245-1_l_4.jpg",
    "title": "原来你是这样的宋朝（袁腾飞作长序力荐）",
    "url": "http://product.dangdang.com/24025245.html",
    "author": "吴钩 著",
    "time": "2016-09-01",
    "press": "长江文艺出版社",
    "prices": "¥27.40"
}, {
    "pic": "http://img3x5.ddimg.cn/96/12/24037395-1_l_3.jpg",
    "title": "至简中国史：大数据讲述中国大历史",
    "url": "http://product.dangdang.com/24037395.html",
    "author": "弘亿",
    "time": "2016-10-01",
    "press": "中国法制出版社",
    "prices": "¥27.50"
}, {
    "pic": "http://img3x6.ddimg.cn/60/22/24032706-1_l_6.jpg",
    "title": "中国历史研究手册（全三册）",
    "url": "http://product.dangdang.com/24032706.html",
    "author": "(英)魏根深,Endymion Wilkinson",
    "time": "2016-09-18",
    "press": "北京大学出版社",
    "prices": "¥150.40"
}, {
    "pic": "http://img3x3.ddimg.cn/46/35/24018733-1_l_5.jpg",
    "title": "易中天中华史 第十七卷：大宋革新（易中天中华史最新卷，讲述不同以往的大宋风云）",
    "url": "http://product.dangdang.com/24018733.html",
    "author": "易中天",
    "time": "2016-09-06",
    "press": "浙江文艺出版社",
    "prices": "¥28.50"
}, {
    "pic": "http://img3x5.ddimg.cn/59/9/23838665-1_l_6.jpg",
    "title": "中国近代史(中国近代史的开山之作，公认的中国近代外交史专家和这一研究领域的开拓者，铁嘴李敖备极推崇。)",
    "url": "http://product.dangdang.com/23838665.html",
    "author": "蒋廷黻",
    "time": "2016-01-01",
    "press": "中国华侨出版社",
    "prices": "¥21.00¥7.00"
}, {
    "pic": "http://img3x0.ddimg.cn/94/34/24018880-1_l_5.jpg",
    "title": "红军长征热点面对面",
    "url": "http://product.dangdang.com/24018880.html",
    "author": "石仲泉",
    "time": "2016-08-01",
    "press": "广东教育出版社",
    "prices": "¥33.60"
}, {
    "pic": "http://img3x0.ddimg.cn/32/5/24017630-1_l_6.jpg",
    "title": "丝绸之路：一部全新的世界史（两千年来始终主宰人类文明的世界十字路口）",
    "url": "http://product.dangdang.com/24017630.html",
    "author": "（英）彼得.弗兰科潘 (Peter Frankopan)",
    "time": "2016-08-17",
    "press": "浙江大学出版社",
    "prices": "¥87.70"
}, {
    "pic": "http://img3x5.ddimg.cn/63/13/24029145-1_l_4.jpg",
    "title": "北上：党中央与张国焘斗争始末",
    "url": "http://product.dangdang.com/24029145.html",
    "author": "刘统",
    "time": "2016-09-01",
    "press": "生活.读书.新知三联书店",
    "prices": "¥47.20"
}, {
    "pic": "http://img3x0.ddimg.cn/73/24/24014800-1_l_5.jpg",
    "title": "欧洲王室另类史",
    "url": "http://product.dangdang.com/24014800.html",
    "author": "（美）法夸尔　著，康怡　译",
    "time": "2016-08-01",
    "press": "生活.读书.新知三联书店",
    "prices": "¥30.40"
}, {
    "pic": "http://img3x9.ddimg.cn/27/3/24022179-1_l_5.jpg",
    "title": "人类砍头小史",
    "url": "http://product.dangdang.com/24022179.html",
    "author": "[英]弗朗西斯・拉尔森（Frances,Larson） 著，秦传安  译;",
    "time": "2016-08-01",
    "press": "海南出版社",
    "prices": "¥34.40¥6.99"
}, {
    "pic": "http://img3x6.ddimg.cn/1/23/24024826-1_l_2.jpg",
    "title": "冷月孤灯 静远楼读史",
    "url": "http://product.dangdang.com/24024826.html",
    "author": "唐浩明",
    "time": "2016-09-01",
    "press": "广东人民出版社",
    "prices": "¥40.30"
}, {
    "pic": "http://img3x1.ddimg.cn/56/23/23953601-1_l_6.jpg",
    "title": "中国通史（经典收藏版）史学大师写给普通读者的国史入门书，与钱穆《国史大纲》双峰对峙的国史巨作。",
    "url": "http://product.dangdang.com/23953601.html",
    "author": "吕思勉",
    "time": "2016-06-01",
    "press": "中国华侨出版社",
    "prices": "¥24.70"
}, {
    "pic": "http://img3x3.ddimg.cn/63/25/24025383-1_l_5.jpg",
    "title": "另一个世界――中国记忆1961-1962（林西莉著）",
    "url": "http://product.dangdang.com/24025383.html",
    "author": "（瑞典）林西莉 著、李之义 译",
    "time": "2016-09-01",
    "press": "中华书局",
    "prices": "¥62.30"
}, {
    "pic": "http://img3x1.ddimg.cn/62/31/24027461-1_l_6.jpg",
    "title": "一个人的世界史  签章版",
    "url": "http://product.dangdang.com/24027461.html",
    "author": "余世存",
    "time": "2016-07-01",
    "press": "广东人民出版社",
    "prices": "¥33.80"
}, {
    "pic": "http://img3x3.ddimg.cn/19/19/24021973-1_l_12.jpg",
    "title": "犹太人的故事:寻找失落的字符",
    "url": "http://product.dangdang.com/24021973.html",
    "author": "[英]西门・沙马（SIMON SCHAMA) 著  黄福武 黄梦初  译",
    "time": "2016-08-01",
    "press": "化学工业出版社",
    "prices": "¥48.20¥19.96"
}, {
    "pic": "http://img3x1.ddimg.cn/94/19/24021751-1_l_5.jpg",
    "title": "不含传说的普鲁士",
    "url": "http://product.dangdang.com/24021751.html",
    "author": "(德)塞巴斯提安・哈夫纳",
    "time": "2016-08-30",
    "press": "北京大学出版社",
    "prices": "¥36.00"
}, {
    "pic": "http://img3x3.ddimg.cn/68/24/24019943-1_l_6.jpg",
    "title": "谁在收藏中国：美国猎获亚洲艺术珍宝百年记",
    "url": "http://product.dangdang.com/24019943.html",
    "author": "【美】谢林・布里萨克、卡尔・梅耶 著；张建新、张紫微 译",
    "time": "2016-09-14",
    "press": "中信出版社",
    "prices": "¥51.00"
}, {
    "pic": "http://img3x3.ddimg.cn/66/32/24037563-1_l_6.jpg",
    "title": "老照片（第108辑）",
    "url": "http://product.dangdang.com/24037563.html",
    "author": "冯克力",
    "time": "2016-08-01",
    "press": "山东画报出版社",
    "prices": "¥15.00"
}, {
    "pic": "http://img3x8.ddimg.cn/34/32/24014068-1_l_6.jpg",
    "title": "王朝的家底：从经济学角度看中国历史",
    "url": "http://product.dangdang.com/24014068.html",
    "author": "波音",
    "time": "2016-08-01",
    "press": "群言出版社",
    "prices": "¥23.80"
}, {
    "pic": "http://img3x8.ddimg.cn/54/1/24031908-1_l_3.jpg",
    "title": "哈佛中国史：精装套装版(全6册)",
    "url": "http://product.dangdang.com/24031908.html",
    "author": "[加]卜正民 [美]陆威仪 [德]迪特?库恩 [美]罗威廉 著；潘玮琳 等 译",
    "time": "2016-10-13",
    "press": "中信出版社",
    "prices": "¥318.20"
}, {
    "pic": "http://img3x3.ddimg.cn/11/32/24017213-1_l_5.jpg",
    "title": "殊方未远：古代中国的疆域、民族与认同",
    "url": "http://product.dangdang.com/24017213.html",
    "author": "葛兆光、徐文堪、汪荣祖、姚大力 等著；《东方早报?上海书评》编辑部 编",
    "time": "2016-08-01",
    "press": "中华书局",
    "prices": "¥53.30"
}, {
    "pic": "http://img3x9.ddimg.cn/75/18/24016089-1_l_6.jpg",
    "title": "历史的砝码：从边缘影响历史的11个人",
    "url": "http://product.dangdang.com/24016089.html",
    "author": "曾纪鑫",
    "time": "2016-08-01",
    "press": "九州出版社",
    "prices": "¥31.50"
}, {
    "pic": "http://img3x5.ddimg.cn/59/21/24032705-1_l_6.jpg",
    "title": "中国经学史大纲",
    "url": "http://product.dangdang.com/24032705.html",
    "author": "叶纯芳",
    "time": "2016-09-18",
    "press": "北京大学出版社",
    "prices": "¥62.40"
}, {
    "pic": "http://img3x1.ddimg.cn/16/5/24040681-1_l_2.jpg",
    "title": "两岸新编中国近代史・晚清卷（全2册）",
    "url": "http://product.dangdang.com/24040681.html",
    "author": "王建朗 黄克武",
    "time": "2016-10-01",
    "press": "社会科学文献出版社",
    "prices": "¥201.00"
}, {
    "pic": "http://img3x0.ddimg.cn/93/4/24039570-1_l_3.jpg",
    "title": "胡马阴山――汉匈五百年战争史",
    "url": "http://product.dangdang.com/24039570.html",
    "author": "顾晓绿",
    "time": "2016-09-01",
    "press": "团结出版社",
    "prices": "¥22.10"
}, {
    "pic": "http://img3x0.ddimg.cn/37/0/24032980-1_l_2.jpg",
    "title": "战国史",
    "url": "http://product.dangdang.com/24032980.html",
    "author": "杨宽  著",
    "time": "2016-07-01",
    "press": "上海人民出版社",
    "prices": "¥78.40"
}, {
    "pic": "http://img3x0.ddimg.cn/97/18/24013240-1_l_6.jpg",
    "title": "古拉格之恋：一个爱情与求生的真实故事（理想国译丛015）",
    "url": "http://product.dangdang.com/24013240.html",
    "author": "[英] 奥兰多・费吉斯",
    "time": "2016-08-01",
    "press": "广西师范大学出版社",
    "prices": "¥48.00"
}, {
    "pic": "http://img3x1.ddimg.cn/58/12/24033991-1_l_4.jpg",
    "title": "纵乐的困惑: 明代的商业与文化",
    "url": "http://product.dangdang.com/24033991.html",
    "author": "[加] 卜正民",
    "time": "2016-10-01",
    "press": "广西师范大学出版社",
    "prices": "¥38.90"
}, {
    "pic": "http://img3x1.ddimg.cn/28/28/24032971-1_l_3.jpg",
    "title": "西周史",
    "url": "http://product.dangdang.com/24032971.html",
    "author": "杨宽 著",
    "time": "2016-07-01",
    "press": "上海人民出版社",
    "prices": "¥94.40"
}, {
    "pic": "http://img3x2.ddimg.cn/22/2/24023362-1_l_1.jpg",
    "title": "说天国：洪秀全真相",
    "url": "http://product.dangdang.com/24023362.html",
    "author": "陶短房　著",
    "time": "2016-06-01",
    "press": "中华书局",
    "prices": "¥36.90"
}, {
    "pic": "http://img3x7.ddimg.cn/58/7/24021517-1_l_5.jpg",
    "title": "奥斯维辛：一部历史（理想国译丛017）",
    "url": "http://product.dangdang.com/24021517.html",
    "author": "劳伦斯・里斯",
    "time": "2016-09-01",
    "press": "广西师范大学出版社",
    "prices": "¥48.00"
}, {
    "pic": "http://img3x9.ddimg.cn/91/11/24027589-1_l_1.jpg",
    "title": "清史讲义（跟大师学国学・精装版）",
    "url": "http://product.dangdang.com/24027589.html",
    "author": "孟森　著",
    "time": "2016-06-01",
    "press": "中华书局",
    "prices": "¥24.60"
}, {
    "pic": "http://img3x4.ddimg.cn/18/24/24023754-1_l_6.jpg",
    "title": "一百个人的十年（精装本）",
    "url": "http://product.dangdang.com/24023754.html",
    "author": "冯骥才",
    "time": "2016-06-01",
    "press": "文化艺术出版社",
    "prices": "¥46.40"
}, {
    "pic": "http://img3x4.ddimg.cn/76/12/24017674-1_l_5.jpg",
    "title": "1493：物种大交换开创的世界史",
    "url": "http://product.dangdang.com/24017674.html",
    "author": "[美]查尔斯?曼恩（Charles C.Mann） 著；朱菲 王原 房小捷 李正行 译",
    "time": "2016-09-13",
    "press": "中信出版社",
    "prices": "¥59.30"
}, {
    "pic": "http://img3x1.ddimg.cn/94/5/24039571-1_l_2.jpg",
    "title": "纵横塞北――元末乱世和明帝国的崛起",
    "url": "http://product.dangdang.com/24039571.html",
    "author": "赵恺、顾晓绿",
    "time": "2016-09-01",
    "press": "团结出版社",
    "prices": "¥22.10"
}, {
    "pic": "http://img3x9.ddimg.cn/92/3/24039569-1_l_3.jpg",
    "title": "东海博弈――明帝国与日本的三百年战史",
    "url": "http://product.dangdang.com/24039569.html",
    "author": "赵恺",
    "time": "2016-09-01",
    "press": "团结出版社",
    "prices": "¥24.80"
}, {
    "pic": "http://img3x8.ddimg.cn/91/2/24039568-1_l_2.jpg",
    "title": "大漠烽烟――唐帝国战争史",
    "url": "http://product.dangdang.com/24039568.html",
    "author": "顾晓绿、赵恺",
    "time": "2016-09-01",
    "press": "团结出版社",
    "prices": "¥26.20"
}, {
    "pic": "http://img3x6.ddimg.cn/89/0/24039566-1_l_3.jpg",
    "title": "八旗狂飙――明清百年战争史",
    "url": "http://product.dangdang.com/24039566.html",
    "author": "顾晓绿 郭强",
    "time": "2016-09-01",
    "press": "团结出版社",
    "prices": "¥24.80"
}, {
    "pic": "http://img3x3.ddimg.cn/5/9/24030473-1_l_5.jpg",
    "title": "文明的滴定：东西方的科学与社会(科学史译丛)",
    "url": "http://product.dangdang.com/24030473.html",
    "author": "[英]李约瑟 著，张卜天 译",
    "time": "2016-08-01",
    "press": "商务印书馆",
    "prices": "¥50.20"
}, {
    "pic": "http://img3x1.ddimg.cn/45/34/24029721-1_l_6.jpg",
    "title": "黑暗大陆",
    "url": "http://product.dangdang.com/24029721.html",
    "author": "[英] 马克?马佐尔（Mark Mazower） 著；赵博文 译",
    "time": "2016-09-29",
    "press": "中信出版社",
    "prices": "¥36.00"
}]
